qualifier/__init__.py
qualifier/executor.py
qualifier-1.6.0.dist-info/METADATA
qualifier-1.6.0.dist-info/WHEEL
qualifier-1.6.0.dist-info/entry_points.txt
qualifier-1.6.0.dist-info/top_level.txt
qualifier-1.6.0.dist-info/RECORD
