Metadata-Version: 2.1
Name: qualifier
Version: 1.6.0
Summary: A simple python project used for updating the qualifier part of the version for python projects.
Home-page: https://github.com/srikalyan/qualifier
Author: Srikalyan Swayampakula
Author-email: srikalyansswayam@gmail.com
License: UNKNOWN
Platform: UNKNOWN
